keycrypt.py
keycrypt-1.0.0.dist-info/LICENSE
keycrypt-1.0.0.dist-info/METADATA
keycrypt-1.0.0.dist-info/WHEEL
keycrypt-1.0.0.dist-info/top_level.txt
keycrypt-1.0.0.dist-info/RECORD
