Metadata-Version: 2.1
Name: keycrypt
Version: 1.0.0
Summary: This package helps you to call secret words used in your script (such as passwords) with the help of Environment Variables without specifying it.
Author-email: Sajad Khanbabaie <khanbabaie.sa@gmail.com>
Project-URL: Homepage, https://github.com/sajad-git/keycrypt
Classifier: Programming Language :: Python :: 3
Classifier: License :: OSI Approved :: MIT License
Classifier: Operating System :: OS Independent
Requires-Python: >=3.6
License-File: LICENSE
